{"Art Nouveau": "conceptnet:art_nouveau", "Baroque": "conceptnet:baroque", "Expressionism": "conceptnet:expressionism", "Impressionism": "conceptnet:impressionism", "Post-Impressionism": "conceptnet:post_impressionism", "Realism": "conceptnet:realism", "Renaissance": "conceptnet:renaissance", "Romanticism": "conceptnet:romanticism", "Surrealism": "conceptnet:surrealism", "Ukiyo-e": "conceptnet:ukiyo_e", "person": "conceptnet:person", "bicycle": "conceptnet:bicycle", "car": "conceptnet:car", "motorcycle": "conceptnet:motorcycle", "airplane": "conceptnet:airplane", "bus": "conceptnet:bus", "train": "conceptnet:train", "truck": "conceptnet:truck", "boat": "conceptnet:boat", "traffic light": "conceptnet:traffic_light", "fire hydrant": "conceptnet:fire_hydrant", "stop sign": "conceptnet:stop_sign", "parking meter": "conceptnet:parking_meter", "bench": "conceptnet:bench", "bird": "conceptnet:bird", "cat": "conceptnet:cat", "dog": "conceptnet:dog", "horse": "conceptnet:horse", "sheep": "conceptnet:sheep", "cow": "conceptnet:cow", "elephant": "conceptnet:elephant", "bear": "conceptnet:bear", "zebra": "conceptnet:zebra", "giraffe": "conceptnet:giraffe", "backpack": "conceptnet:backpack", "umbrella": "conceptnet:umbrella", "handbag": "conceptnet:handbag", "tie": "conceptnet:tie", "suitcase": "conceptnet:suitcase", "frisbee": "conceptnet:frisbee", "skis": "conceptnet:skis", "snowboard": "conceptnet:snowboard", "sports ball": "conceptnet:sports_ball", "kite": "conceptnet:kite", "baseball bat": "conceptnet:baseball_bat", "baseball glove": "conceptnet:baseball_glove", "skateboard": "conceptnet:skateboard", "surfboard": "conceptnet:surfboard", "tennis racket": "conceptnet:tennis_racket", "bottle": "conceptnet:bottle", "wine glass": "conceptnet:wine_glass", "cup": "conceptnet:cup", "fork": "conceptnet:fork", "knife": "conceptnet:knife", "spoon": "conceptnet:spoon", "bowl": "conceptnet:bowl", "banana": "conceptnet:banana", "apple": "conceptnet:apple", "sandwich": "conceptnet:sandwich", "orange": "conceptnet:orange", "broccoli": "conceptnet:broccoli", "carrot": "conceptnet:carrot", "hot dog": "conceptnet:hot_dog", "pizza": "conceptnet:pizza", "donut": "conceptnet:donut", "cake": "conceptnet:cake", "chair": "conceptnet:chair", "couch": "conceptnet:couch", "potted plant": "conceptnet:potted_plant", "bed": "conceptnet:bed", "dining table": "conceptnet:dining_table", "toilet": "conceptnet:toilet", "tv": "conceptnet:tv", "laptop": "conceptnet:laptop", "mouse": "conceptnet:mouse", "remote": "conceptnet:remote", "keyboard": "conceptnet:keyboard", "cell phone": "conceptnet:cell_phone", "microwave": "conceptnet:microwave", "oven": "conceptnet:oven", "toaster": "conceptnet:toaster", "sink": "conceptnet:sink", "refrigerator": "conceptnet:refrigerator", "book": "conceptnet:book", "clock": "conceptnet:clock", "vase": "conceptnet:vase", "scissors": "conceptnet:scissors", "teddy bear": "conceptnet:teddy_bear", "hair drier": "conceptnet:hair_drier", "toothbrush": "conceptnet:toothbrush", "amusement": "conceptnet:amusement", "awe": "conceptnet:awe", "contentment": "conceptnet:contentment", "excitement": "conceptnet:excitement", "anger": "conceptnet:anger", "disgust": "conceptnet:disgust", "fear": "conceptnet:fear", "sadness": "conceptnet:sadness", "something else": "conceptnet:something_else", "alice blue": "conceptnet:alice_blue", "antique white": "conceptnet:antique_white", "aqua": "conceptnet:aqua", "aquamarine": "conceptnet:aquamarine", "azure": "conceptnet:azure", "beige": "conceptnet:beige", "bisque": "conceptnet:bisque", "black": "conceptnet:black", "blanched almond": "conceptnet:blanched_almond", "blue": "conceptnet:blue", "blue violet": "conceptnet:blue_violet", "brown": "conceptnet:brown", "burly wood": "conceptnet:wood", "cadet blue": "conceptnet:cadet_blue", "chartreuse": "conceptnet:chartreuse", "chocolate": "conceptnet:chocolate", "coral": "conceptnet:coral", "cornflower blue": "conceptnet:cornflower_blue", "cornsilk": "conceptnet:cornsilk", "crimson": "conceptnet:crimson", "cyan": "conceptnet:cyan", "dark blue": "conceptnet:dark_blue", "dark cyan": "conceptnet:cyan", "dark goldenrod": "conceptnet:goldenrod", "dark gray": "conceptnet:dark_gray", "dark green": "conceptnet:dark_green", "dark grey": "conceptnet:dark_grey", "dark khaki": "conceptnet:khaki", "dark magenta": "conceptnet:magenta", "dark olive green": "conceptnet:olive_green", "dark orange": "conceptnet:dark_orange", "dark orchid": "conceptnet:orchid", "dark red": "conceptnet:dark_red", "dark salmon": "conceptnet:salmon", "dark sea green": "conceptnet:dark_sea_green", "dark slate blue": "conceptnet:slate_blue", "dark slate gray": "conceptnet:slate_gray", "dark slate grey": "conceptnet:slate_grey", "dark turquoise": "conceptnet:turquoise", "dark violet": "conceptnet:violet", "deep pink": "conceptnet:deep_pink", "deep sky blue": "conceptnet:sky_blue", "dim gray": "conceptnet:gray", "dim grey": "conceptnet:grey", "dodger blue": "conceptnet:dodger_blue", "firebrick": "conceptnet:firebrick", "floral white": "conceptnet:floral_white", "forest green": "conceptnet:forest_green", "fuchsia": "conceptnet:fuchsia", "gainsboro": "conceptnet:gainsboro", "ghost white": "conceptnet:white", "gold": "conceptnet:gold", "goldenrod": "conceptnet:goldenrod", "gray": "conceptnet:gray", "green": "conceptnet:green", "green yellow": "conceptnet:green_yellow", "grey": "conceptnet:grey", "honeydew": "conceptnet:honeydew", "hot pink": "conceptnet:hot_pink", "indian red": "conceptnet:indian_red", "indigo": "conceptnet:indigo", "ivory": "conceptnet:ivory", "khaki": "conceptnet:khaki", "lavender": "conceptnet:lavender", "lavender blush": "conceptnet:blush", "lawn green": "conceptnet:green", "lemon chiffon": "conceptnet:lemon_chiffon", "light blue": "conceptnet:light_blue", "light coral": "conceptnet:coral", "light cyan": "conceptnet:cyan", "light goldenrod yellow": "conceptnet:goldenrod_yellow", "light gray": "conceptnet:light_gray", "light green": "conceptnet:light_green", "light grey": "conceptnet:light_grey", "light pink": "conceptnet:light_pink", "light salmon": "conceptnet:salmon", "light sea green": "conceptnet:sea_green", "light sky blue": "conceptnet:sky_blue", "light slate gray": "conceptnet:slate_gray", "light slate grey": "conceptnet:slate_grey", "light steel blue": "conceptnet:steel_blue", "light yellow": "conceptnet:light_yellow", "lime": "conceptnet:lime", "lime green": "conceptnet:lime_green", "linen": "conceptnet:linen", "magenta": "conceptnet:magenta", "maroon": "conceptnet:maroon", "medium aquamarine": "conceptnet:aquamarine", "medium blue": "conceptnet:blue", "medium orchid": "conceptnet:orchid", "medium purple": "conceptnet:purple", "medium sea green": "conceptnet:sea_green", "medium slate blue": "conceptnet:slate_blue", "medium spring green": "conceptnet:spring_green", "medium turquoise": "conceptnet:turquoise", "medium violet red": "conceptnet:violet_red", "midnight blue": "conceptnet:midnight_blue", "mint cream": "conceptnet:mint_cream", "misty rose": "conceptnet:misty_rose", "moccasin": "conceptnet:moccasin", "navajo white": "conceptnet:navajo_white", "navy": "conceptnet:navy", "old lace": "conceptnet:old_lace", "olive": "conceptnet:olive", "olive drab": "conceptnet:olive_drab", "orange red": "conceptnet:orange_red", "orchid": "conceptnet:orchid", "pale goldenrod": "conceptnet:goldenrod", "pale green": "conceptnet:pale_green", "pale turquoise": "conceptnet:turquoise", "pale violet red": "conceptnet:violet_red", "papaya whip": "conceptnet:whip", "peach puff": "conceptnet:puff", "peru": "conceptnet:peru", "pink": "conceptnet:pink", "plum": "conceptnet:plum", "powder blue": "conceptnet:powder_blue", "purple": "conceptnet:purple", "red": "conceptnet:red", "rosy brown": "conceptnet:brown", "royal blue": "conceptnet:royal_blue", "saddle brown": "conceptnet:saddle_brown", "salmon": "conceptnet:salmon", "sandy brown": "conceptnet:brown", "sea green": "conceptnet:sea_green", "seashell": "conceptnet:seashell", "sienna": "conceptnet:sienna", "silver": "conceptnet:silver", "sky blue": "conceptnet:sky_blue", "slate blue": "conceptnet:slate_blue", "slate gray": "conceptnet:slate_gray", "slate grey": "conceptnet:slate_grey", "snow": "conceptnet:snow", "spring green": "conceptnet:spring_green", "steel blue": "conceptnet:steel_blue", "tan": "conceptnet:tan", "teal": "conceptnet:teal", "thistle": "conceptnet:thistle", "tomato": "conceptnet:tomato", "turquoise": "conceptnet:turquoise", "violet": "conceptnet:violet", "wheat": "conceptnet:wheat", "white": "conceptnet:white", "white smoke": "conceptnet:white_smoke", "yellow": "conceptnet:yellow", "yellow green": "conceptnet:yellow_green", "calling": "conceptnet:calling", "clapping": "conceptnet:clapping", "cycling": "conceptnet:cycling", "dancing": "conceptnet:dancing", "drinking": "conceptnet:drinking", "eating": "conceptnet:eating", "fighting": "conceptnet:fighting", "hugging": "conceptnet:hugging", "laughing": "conceptnet:laughing", "listening_to_music": "conceptnet:listening_to_music", "running": "conceptnet:running", "sitting": "conceptnet:sitting", "sleeping": "conceptnet:sleeping", "texting": "conceptnet:texting", "using_laptop": "conceptnet:laptop"}